{
  "data": {
    "canJoinMidway": false,
    "fixed_viewPos": {
      "pos": {
        "__OBJ_TYPE": "Vector3i"
      }
    },
    "initPos": {
      "map": "map001",
      "pos": {
        "x": 20,
        "y": 1.04,
        "z": 46
      }
    },
    "nowTime": {
      "h": 7,
      "m": 40
    },
    "player_range": {
      "max": 6,
      "min": 1
    },
    "startPos": {
      "map": "713abf64-d7a6-451d-99bb-cc542da2b849",
      "pos": {
        "x": -20,
        "y": 1,
        "z": 46
      }
    },
    "unlimitedPlayTime": true,
    "vars": {
      "entity": [
        {
          "key": "isOpen",
          "save": true,
          "type": "bool",
          "value": {
            "__OBJ_TYPE": "T_Bool"
          }
        }
      ],
      "global": [
        {
          "key": "isCheck",
          "type": "bool",
          "value": {
            "__OBJ_TYPE": "T_Bool"
          }
        },
        {
          "key": "player",
          "type": "entity",
          "value": {
            "__OBJ_TYPE": "T_Entity"
          }
        },
        {
          "key": "haveKey",
          "type": "bool",
          "value": {
            "__OBJ_TYPE": "T_Bool"
          }
        },
        {
          "key": "mainKey",
          "type": "bool",
          "value": {
            "__OBJ_TYPE": "T_Bool"
          }
        }
      ]
    }
  },
  "meta": {
    "EXPORT": {
      "setting.json": "da7e183b7b53a41296c9f1f5333f008f",
      "shop.csv": "393e9a440b900b5690986ec2b0e57be5",
      "triggers.bts": "",
      "triggers_client.bts": ""
    },
    "VERSION": "0.24"
  }
}