{
  "data": {
    "md5": "27294bc72e4f91609999e123258cea3f",
    "path": "gui/layout_presets/chat.layout",
    "root": {
      "children": [
        {
          "__OBJ_TYPE": "DefaultWindow",
          "children": [
            {
              "__OBJ_TYPE": "StaticImage",
              "Alpha": 0.5,
              "BackgroundColours": {
                "b": 0,
                "g": 0,
                "r": 0
              },
              "BackgroundEnabled": true,
              "id": {
                "value": "d9035eef-eb7e-458c-aff3-5332b9932cf7"
              },
              "Image": {
                "asset": "",
                "selector": ""
              },
              "lock": true,
              "name": "Chat_Content_Bg",
              "size": {
                "UDim_X": {
                  "Offect": 0,
                  "Scale": 1
                },
                "UDim_Y": {
                  "Offect": 0,
                  "Scale": 1
                }
              }
            }
          ],
          "id": {
            "value": "b3f6ba59-5a2a-4f64-84df-2c18c8ce2832"
          },
          "lock": true,
          "name": "Chat_Content",
          "size": {
            "UDim_X": {
              "Offect": 0,
              "Scale": 1
            },
            "UDim_Y": {
              "Offect": 270
            }
          }
        },
        {
          "__OBJ_TYPE": "ScrollableView",
          "BackGroundImage": {
            "asset": "",
            "selector": ""
          },
          "children": [
            {
              "__OBJ_TYPE": "StaticImage",
              "id": {
                "value": "7b6f32e0-dc1a-4242-9696-9635379cb0e9"
              },
              "Image": {
                "asset": "",
                "selector": ""
              },
              "lock": true,
              "name": "Chat_Content_Mask",
              "size": {
                "UDim_X": {
                  "Offect": 0,
                  "Scale": 1
                },
                "UDim_Y": {
                  "Offect": 0,
                  "Scale": 1
                }
              }
            },
            {
              "__OBJ_TYPE": "VerticalLayoutContainer",
              "id": {
                "value": "92054330-e871-4ad4-83d2-b16c1054a8e0"
              },
              "lock": true,
              "name": "Chat_Content_MsgList",
              "space": 1,
              "WindowTouchThroughMode": "MousePassThroughOpen"
            }
          ],
          "ForceHorzScrollbar": false,
          "ForceVertScrollbar": false,
          "HorizontalMovable": false,
          "id": {
            "value": "946fe011-798f-4481-95ec-397a5b9cfa0c"
          },
          "lock": true,
          "name": "Chat_Content_ScrollableView",
          "pos": {
            "UDim_X": {
              "Offect": 20
            }
          },
          "size": {
            "UDim_X": {
              "Offect": -20,
              "Scale": 1
            },
            "UDim_Y": {
              "Offect": -79.461003303523,
              "Scale": 1
            }
          }
        },
        {
          "__OBJ_TYPE": "DefaultWindow",
          "anchor": {
            "VerticalAlignment": "Bottom"
          },
          "children": [
            {
              "__OBJ_TYPE": "StaticImage",
              "Alpha": 0.5,
              "BackgroundColours": {
                "b": 0,
                "g": 0,
                "r": 0
              },
              "BackgroundEnabled": true,
              "id": {
                "value": "57906a9d-bec8-40b3-b9f9-efc707a3803d"
              },
              "Image": {
                "asset": "",
                "selector": ""
              },
              "lock": true,
              "name": "Chat_SendLayout_Bg",
              "size": {
                "UDim_X": {
                  "Offect": 0,
                  "Scale": 1
                },
                "UDim_Y": {
                  "Offect": 0,
                  "Scale": 1
                }
              }
            },
            {
              "__OBJ_TYPE": "DefaultWindow",
              "anchor": {
                "VerticalAlignment": "Centre"
              },
              "children": [
                {
                  "__OBJ_TYPE": "StaticImage",
                  "Alpha": 0.35,
                  "BackgroundColours": {
                    "b": 161,
                    "g": 162,
                    "r": 163
                  },
                  "BackgroundEnabled": true,
                  "id": {
                    "value": "231b9290-14f1-4cfe-9772-4ce987f4e4de"
                  },
                  "Image": {
                    "asset": "",
                    "selector": ""
                  },
                  "lock": true,
                  "name": "Chat_SendLayout_Input_Bg",
                  "size": {
                    "UDim_X": {
                      "Offect": 0,
                      "Scale": 1
                    },
                    "UDim_Y": {
                      "Offect": 0,
                      "Scale": 1
                    }
                  }
                },
                {
                  "__OBJ_TYPE": "Editbox",
                  "BackGroundImage": {
                    "asset": "",
                    "selector": ""
                  },
                  "Font_size": 16,
                  "id": {
                    "value": "1c09f8cc-8bc3-4580-bf8c-e4e1bb0c7114"
                  },
                  "lock": true,
                  "MaxTextLength": 10,
                  "name": "Chat_SendLayout_Input_Btn",
                  "NormalTextColour": {
                    "b": 255,
                    "g": 255,
                    "r": 255
                  },
                  "pos": {
                    "UDim_X": {
                      "Offect": 1.0773121118553
                    }
                  },
                  "size": {
                    "UDim_X": {
                      "Offect": -1.19209360005534e-06,
                      "Scale": 1
                    },
                    "UDim_Y": {
                      "Offect": 0,
                      "Scale": 1
                    }
                  },
                  "text_key": {
                    "value": "gui/layout_presets/chat.layout.Editbox#68a9a215-3927-46c3-867f-d6403f4ad432"
                  }
                }
              ],
              "id": {
                "value": "f7b8b0ab-cea1-4d59-af3d-411497df2142"
              },
              "lock": true,
              "name": "Chat_SendLayout_Input",
              "pos": {
                "UDim_X": {
                  "Offect": 55
                }
              },
              "size": {
                "UDim_X": {
                  "Offect": -31.3,
                  "Scale": 0.85
                },
                "UDim_Y": {
                  "Offect": 50
                }
              }
            },
            {
              "__OBJ_TYPE": "Button",
              "anchor": {
                "HorizontalAlignment": "Right",
                "VerticalAlignment": "Centre"
              },
              "DisabledImage": {
                "asset": "",
                "selector": ""
              },
              "HoverImage": {
                "asset": "asset/Texture/Gui/imagesets/cegui_new_gameUI.imageset",
                "imageset_key": "icon_sendMsg_nor",
                "selector": "asset/Texture/Gui/imagesets/cegui_new_gameUI.imageset"
              },
              "id": {
                "value": "37512010-062c-4dd8-8237-087b0e14c307"
              },
              "lock": true,
              "name": "Chat_SendLayout_SendMsg",
              "NormalImage": {
                "asset": "asset/Texture/Gui/imagesets/cegui_new_gameUI.imageset",
                "imageset_key": "icon_sendMsg_nor",
                "selector": "asset/Texture/Gui/imagesets/cegui_new_gameUI.imageset"
              },
              "pos": {
                "UDim_X": {
                  "Offect": -9.6134124994275
                }
              },
              "PushedImage": {
                "asset": "asset/Texture/Gui/imagesets/cegui_new_gameUI.imageset",
                "imageset_key": "icon_sendMsg_act",
                "selector": "asset/Texture/Gui/imagesets/cegui_new_gameUI.imageset"
              },
              "size": {
                "UDim_X": {
                  "Offect": 39.9999999999995
                },
                "UDim_Y": {
                  "Offect": 40
                }
              },
              "Text": "",
              "text_key": {
                "value": "gui/layout_presets/chat.layout.Button#e3099da0-8f69-433d-9526-4f71ad81b0bb"
              }
            },
            {
              "__OBJ_TYPE": "DefaultWindow",
              "children": [
                {
                  "__OBJ_TYPE": "VerticalLayoutContainer",
                  "children": [
                    {
                      "__OBJ_TYPE": "DefaultWindow",
                      "children": [
                        {
                          "__OBJ_TYPE": "StaticImage",
                          "id": {
                            "value": "c84ee0fd-79dc-4ba3-992c-ad1c60cf1d2d"
                          },
                          "Image": {
                            "asset": "asset/Texture/Gui/progressbar_bg.png"
                          },
                          "lock": true,
                          "name": "Chat_Friend_Bg",
                          "pos": {
                            "UDim_X": {
                              "Offect": 1.0773109197617
                            }
                          },
                          "size": {
                            "UDim_X": {
                              "Offect": 0,
                              "Scale": 1
                            },
                            "UDim_Y": {
                              "Offect": 0,
                              "Scale": 1
                            }
                          }
                        },
                        {
                          "__OBJ_TYPE": "Button",
                          "children": [
                            {
                              "__OBJ_TYPE": "StaticImage",
                              "id": {
                                "value": "d1ba7913-f3e3-451f-9220-83cbdb82841b"
                              },
                              "Image": {
                                "asset": "",
                                "selector": ""
                              },
                              "lock": true,
                              "name": "Chat_Friend_Head",
                              "pos": {
                                "UDim_X": {
                                  "Offect": 10
                                },
                                "UDim_Y": {
                                  "Offect": 10
                                }
                              },
                              "size": {
                                "UDim_X": {
                                  "Offect": 30
                                },
                                "UDim_Y": {
                                  "Offect": 30
                                }
                              },
                              "WindowTouchThroughMode": "MousePassThroughOpen"
                            },
                            {
                              "__OBJ_TYPE": "StaticText",
                              "Alpha": 0.994,
                              "id": {
                                "value": "94fb6f1b-c997-4e78-8b6c-efd5f9150cf9"
                              },
                              "lock": true,
                              "name": "Chat_Friend_Name",
                              "pos": {
                                "UDim_X": {
                                  "Offect": 53.618493795396
                                }
                              },
                              "size": {
                                "UDim_X": {
                                  "Offect": 174.665427207964
                                },
                                "UDim_Y": {
                                  "Offect": 50
                                }
                              },
                              "Text": "",
                              "text_key": {
                                "value": "gui/layout_presets/chat.layout.StaticText#daf43546-524c-4c45-a0da-5bbf26441b73"
                              },
                              "VertFormatting": "CentreAligned",
                              "WindowTouchThroughMode": "MousePassThroughOpen",
                              "word_warpped": false
                            }
                          ],
                          "DisabledImage": {
                            "asset": "",
                            "selector": ""
                          },
                          "HoverImage": {
                            "asset": "",
                            "selector": ""
                          },
                          "HoverStretch": {
                            "bottom_left": 3,
                            "top_left": 3
                          },
                          "id": {
                            "value": "da2e0eda-7e6e-4f72-9163-24150f3c7edf"
                          },
                          "lock": true,
                          "name": "Chat_Friend_Select_Btn",
                          "NormalImage": {
                            "asset": "",
                            "selector": ""
                          },
                          "NormalStretch": {
                            "bottom_left": 3,
                            "top_left": 3
                          },
                          "pos": {
                            "UDim_X": {
                              "Offect": 10
                            },
                            "UDim_Y": {
                              "Offect": 5
                            }
                          },
                          "PushedStretch": {
                            "bottom_left": 3,
                            "top_left": 3
                          },
                          "size": {
                            "UDim_X": {
                              "Offect": 235
                            },
                            "UDim_Y": {
                              "Offect": 50
                            }
                          },
                          "Text": "",
                          "text_key": {
                            "value": "gui/layout_presets/chat.layout.Button#5eb29ab6-c10e-4495-a37b-66c1844861bf"
                          }
                        }
                      ],
                      "id": {
                        "value": "58dc8dd9-3c99-4798-8823-5f8b1cd7594f"
                      },
                      "lock": true,
                      "name": "Chat_Friend_Item1",
                      "size": {
                        "UDim_X": {
                          "Offect": 255
                        },
                        "UDim_Y": {
                          "Offect": 65
                        }
                      }
                    },
                    {
                      "__OBJ_TYPE": "DefaultWindow",
                      "children": [
                        {
                          "__OBJ_TYPE": "StaticImage",
                          "id": {
                            "value": "091a0ed7-3491-4837-b56d-50f21aa7a4f5"
                          },
                          "Image": {
                            "asset": "asset/Texture/Gui/progressbar_bg.png"
                          },
                          "lock": true,
                          "name": "Chat_Friend_Bg",
                          "pos": {
                            "UDim_X": {
                              "Offect": 1.0773109197617
                            }
                          },
                          "size": {
                            "UDim_X": {
                              "Offect": 0,
                              "Scale": 1
                            },
                            "UDim_Y": {
                              "Offect": 0,
                              "Scale": 1
                            }
                          },
                          "WindowTouchThroughMode": "MousePassThroughOpen"
                        },
                        {
                          "__OBJ_TYPE": "Button",
                          "Alpha": 0.997,
                          "children": [
                            {
                              "__OBJ_TYPE": "StaticImage",
                              "id": {
                                "value": "0f7e0740-1faf-42f8-a858-ad432dcb0005"
                              },
                              "Image": {
                                "asset": "",
                                "selector": ""
                              },
                              "lock": true,
                              "name": "Chat_Friend_Head",
                              "pos": {
                                "UDim_X": {
                                  "Offect": 10
                                },
                                "UDim_Y": {
                                  "Offect": 10
                                }
                              },
                              "size": {
                                "UDim_X": {
                                  "Offect": 30
                                },
                                "UDim_Y": {
                                  "Offect": 30
                                }
                              },
                              "WindowTouchThroughMode": "MousePassThroughOpen"
                            },
                            {
                              "__OBJ_TYPE": "StaticText",
                              "id": {
                                "value": "1dc95232-ac21-41a0-8eeb-a4a5dc9d98f2"
                              },
                              "lock": true,
                              "name": "Chat_Friend_Name",
                              "pos": {
                                "UDim_X": {
                                  "Offect": 53.618493795396
                                }
                              },
                              "size": {
                                "UDim_X": {
                                  "Offect": 174.665427207964
                                },
                                "UDim_Y": {
                                  "Offect": 50
                                }
                              },
                              "Text": "",
                              "text_key": {
                                "value": "gui/layout_presets/chat.layout.StaticText#3cc7f230-0a94-455b-93e0-37e96449bbf7"
                              },
                              "VertFormatting": "CentreAligned",
                              "WindowTouchThroughMode": "MousePassThroughOpen",
                              "word_warpped": false
                            }
                          ],
                          "DisabledImage": {
                            "asset": "",
                            "selector": ""
                          },
                          "HoverImage": {
                            "asset": "",
                            "selector": ""
                          },
                          "HoverStretch": {
                            "bottom_left": 3,
                            "top_left": 3
                          },
                          "id": {
                            "value": "7259ccee-aec5-473c-af8c-16a1fa6691bc"
                          },
                          "lock": true,
                          "name": "Chat_Friend_Select_Btn",
                          "NormalImage": {
                            "asset": "",
                            "selector": ""
                          },
                          "NormalStretch": {
                            "bottom_left": 3,
                            "top_left": 3
                          },
                          "pos": {
                            "UDim_X": {
                              "Offect": 10
                            },
                            "UDim_Y": {
                              "Offect": 5
                            }
                          },
                          "PushedStretch": {
                            "bottom_left": 3,
                            "top_left": 3
                          },
                          "size": {
                            "UDim_X": {
                              "Offect": 235
                            },
                            "UDim_Y": {
                              "Offect": 50
                            }
                          },
                          "Text": "",
                          "text_key": {
                            "value": "gui/layout_presets/chat.layout.Button#a45e1ec2-c029-4aae-9d14-3ce983b4e87f"
                          }
                        }
                      ],
                      "id": {
                        "value": "8f4b4ccc-67d8-4d0a-af41-f0d9e03b049e"
                      },
                      "lock": true,
                      "name": "Chat_Friend_Item2",
                      "pos": {
                        "UDim_Y": {
                          "Offect": 65
                        }
                      },
                      "size": {
                        "UDim_X": {
                          "Offect": 255
                        },
                        "UDim_Y": {
                          "Offect": 65
                        }
                      }
                    },
                    {
                      "__OBJ_TYPE": "DefaultWindow",
                      "children": [
                        {
                          "__OBJ_TYPE": "StaticImage",
                          "id": {
                            "value": "ed017fea-8a37-4f36-9287-8cf921cf0be6"
                          },
                          "Image": {
                            "asset": "asset/Texture/Gui/progressbar_bg.png"
                          },
                          "lock": true,
                          "name": "Chat_Friend_Bg",
                          "pos": {
                            "UDim_X": {
                              "Offect": 1.0773109197617
                            }
                          },
                          "size": {
                            "UDim_X": {
                              "Offect": 0,
                              "Scale": 1
                            },
                            "UDim_Y": {
                              "Offect": 0,
                              "Scale": 1
                            }
                          },
                          "WindowTouchThroughMode": "MousePassThroughOpen"
                        },
                        {
                          "__OBJ_TYPE": "Button",
                          "children": [
                            {
                              "__OBJ_TYPE": "StaticImage",
                              "id": {
                                "value": "580168a5-f832-4a51-b378-7feb20d0b366"
                              },
                              "Image": {
                                "asset": "",
                                "selector": ""
                              },
                              "lock": true,
                              "name": "Chat_Friend_Head",
                              "pos": {
                                "UDim_X": {
                                  "Offect": 10
                                },
                                "UDim_Y": {
                                  "Offect": 10
                                }
                              },
                              "size": {
                                "UDim_X": {
                                  "Offect": 30
                                },
                                "UDim_Y": {
                                  "Offect": 30
                                }
                              },
                              "WindowTouchThroughMode": "MousePassThroughOpen"
                            },
                            {
                              "__OBJ_TYPE": "StaticText",
                              "id": {
                                "value": "9136b7bc-cbab-48b6-81ad-851a08870401"
                              },
                              "lock": true,
                              "name": "Chat_Friend_Name",
                              "pos": {
                                "UDim_X": {
                                  "Offect": 53.618493795396
                                }
                              },
                              "size": {
                                "UDim_X": {
                                  "Offect": 174.665427207964
                                },
                                "UDim_Y": {
                                  "Offect": 50
                                }
                              },
                              "Text": "",
                              "text_key": {
                                "value": "gui/layout_presets/chat.layout.StaticText#de042293-d9b9-4d86-bb75-99cc3b4506b0"
                              },
                              "VertFormatting": "CentreAligned",
                              "WindowTouchThroughMode": "MousePassThroughOpen",
                              "word_warpped": false
                            }
                          ],
                          "HoverImage": {
                            "asset": "",
                            "selector": ""
                          },
                          "HoverStretch": {
                            "bottom_left": 3,
                            "top_left": 3
                          },
                          "id": {
                            "value": "aeb0838c-96d6-4882-8bfc-444938841549"
                          },
                          "lock": true,
                          "name": "Chat_Friend_Select_Btn",
                          "NormalImage": {
                            "asset": "",
                            "selector": ""
                          },
                          "NormalStretch": {
                            "bottom_left": 3,
                            "top_left": 3
                          },
                          "pos": {
                            "UDim_X": {
                              "Offect": 10
                            },
                            "UDim_Y": {
                              "Offect": 5
                            }
                          },
                          "PushedStretch": {
                            "bottom_left": 3,
                            "top_left": 3
                          },
                          "size": {
                            "UDim_X": {
                              "Offect": 235
                            },
                            "UDim_Y": {
                              "Offect": 50
                            }
                          },
                          "Text": "",
                          "text_key": {
                            "value": "gui/layout_presets/chat.layout.Button#07cb88c1-99a3-41b6-a689-4e298aac677f"
                          }
                        }
                      ],
                      "id": {
                        "value": "41e7c96d-ff42-4139-84cd-a1078b29e848"
                      },
                      "lock": true,
                      "name": "Chat_Friend_Item3",
                      "pos": {
                        "UDim_Y": {
                          "Offect": 130
                        }
                      },
                      "size": {
                        "UDim_X": {
                          "Offect": 255
                        },
                        "UDim_Y": {
                          "Offect": 65
                        }
                      }
                    }
                  ],
                  "id": {
                    "value": "6ec12aea-1526-4c1b-8437-2eef794a929b"
                  },
                  "lock": true
                }
              ],
              "id": {
                "value": "263f04fa-c38e-4d64-9124-9bed127cecee"
              },
              "lock": true,
              "name": "Chat_Friend_SelectLayout",
              "pos": {
                "UDim_X": {
                  "Offect": -1.1920880016447e-07
                },
                "UDim_Y": {
                  "Offect": 75
                }
              },
              "size": {
                "UDim_X": {
                  "Offect": 254.999999999999
                },
                "UDim_Y": {
                  "Offect": 180
                }
              },
              "Visible": false
            },
            {
              "__OBJ_TYPE": "Button",
              "DisabledImage": {
                "asset": "",
                "selector": ""
              },
              "HoverImage": {
                "asset": "",
                "selector": ""
              },
              "id": {
                "value": "e0b0571a-c277-4125-ae11-3c8cbc404852"
              },
              "lock": true,
              "name": "Chat_Type_Select_Btn",
              "NormalImage": {
                "asset": "",
                "selector": ""
              },
              "pos": {
                "UDim_X": {
                  "Offect": 10.000002384187
                },
                "UDim_Y": {
                  "Offect": 15
                }
              },
              "PushedImage": {
                "asset": "",
                "selector": ""
              },
              "size": {
                "UDim_X": {
                  "Offect": 40
                },
                "UDim_Y": {
                  "Offect": 40
                }
              },
              "Text": "",
              "text_key": {
                "value": "gui/layout_presets/chat.layout.Button#8ce44d2c-2f8e-42ea-9fc7-59a00d0efa57"
              }
            }
          ],
          "id": {
            "value": "856233d6-8b89-4ced-a38f-4be3470de131"
          },
          "lock": true,
          "name": "Chat_SendLayout",
          "size": {
            "UDim_X": {
              "Offect": 0,
              "Scale": 1
            },
            "UDim_Y": {
              "Offect": 70
            }
          }
        }
      ],
      "id": {
        "value": "cc67ee2e-1c24-4fd8-a1a4-45ee31d4264d"
      },
      "lock": true,
      "pos": {
        "UDim_X": {
          "Offect": 18
        },
        "UDim_Y": {
          "Offect": 70
        }
      },
      "size": {
        "UDim_X": {
          "Offect": 540
        },
        "UDim_Y": {
          "Offect": 350
        }
      }
    }
  },
  "meta": {
    "EXPORT": {
      "layout": "27294bc72e4f91609999e123258cea3f",
      "triggers.bts": "d1fd7037f4941cd1b8cbfb94bb926990"
    },
    "VERSION": "0.24"
  }
}